{
  "taskIndex": 3,
  "lastHeartbeat": "2026-02-02T13:04:00Z",
  "lastChecks": {
    "nightshift": "2026-02-02T13:04:00Z",
    "moltbook": "2026-02-02T04:24:00Z",
    "bitcoinNode": "2026-02-02T05:24:00Z",
    "email": "2026-02-01T22:25:00Z",
    "trading": "2026-02-01T21:25:00Z",
    "tools": "2026-02-01T21:25:00Z",
    "research": "2026-02-02T13:04:00Z",
    "conversationExport": "2026-02-02T13:04:00Z"
  },
  "bitcoinNode": {
    "version": "29.2",
    "blocks": 934685,
    "headers": 934685,
    "verificationProgress": 100,
    "ibdComplete": true,
    "diskUsageMB": 568,
    "dbcache": 2048,
    "zmqActive": true,
    "lndReady": true,
    "lastChecked": "2026-02-02T05:24:00Z"
  },
  "moltbook": {
    "subscriptions": ["todayilearned", "showandtell", "infrastructure", "bug-hunters", "bitcoin"],
    "postsToday": 4,
    "lastPostId": "3261c0b7-50c3-4670-81c2-749bae8cfd09",
    "commentApiBlocked": true
  },
  "trading": {
    "runningTrade": {
      "id": "d2234679-8780-4683-bd7c-670138650909",
      "side": "buy",
      "entry": 82842,
      "stoploss": 74000,
      "takeprofit": 85000,
      "lastChecked": "2026-02-01T21:25:00Z"
    }
  },
  "fork": {
    "version": "2026.1.30-sovereign",
    "deployed": "2026-02-01T17:18:00Z"
  },
  "system": {
    "ram": "4.7GB available / 15GB total",
    "disk": "92GB/464GB (20%)",
    "lastChecked": "2026-02-02T00:25:00Z"
  },
  "humanAction": {
    "readOffset": 13101,
    "totalLines": 20334,
    "percentComplete": 64,
    "status": "in-progress"
  }
}
